{"cameraMode":{"drawMode":0,"name":"Shaded","section":"Shading Mode"},"sceneLighting":true,"audioPlay":false,"sceneViewState":{"m_AlwaysRefresh":false,"showFog":true,"showSkybox":true,"showFlares":true,"showImageEffects":true,"showParticleSystems":true,"showVisualEffectGraphs":true,"m_FxEnabled":true},"in2DMode":false,"pivot":{"x":746.9552001953125,"y":363.0723571777344,"z":22.296630859375},"rotation":{"x":0.01914011873304844,"y":-0.07132931053638458,"z":-0.001369008095934987,"w":-0.9972677826881409},"size":237.5661163330078,"orthographic":false}